main.py
xiaocaiji_text1_mcp_server-0.1.0.dist-info/METADATA
xiaocaiji_text1_mcp_server-0.1.0.dist-info/WHEEL
xiaocaiji_text1_mcp_server-0.1.0.dist-info/top_level.txt
xiaocaiji_text1_mcp_server-0.1.0.dist-info/RECORD
